gate/__init__.py
gate/drift.py
gate/statistics.py
gate/summarize.py
gate/summary.py
gate_drift-0.1.5.dist-info/LICENSE
gate_drift-0.1.5.dist-info/METADATA
gate_drift-0.1.5.dist-info/WHEEL
gate_drift-0.1.5.dist-info/RECORD
